luciusassistant/__init__.py
luciusassistant/builtin_function_calls.py
luciusassistant/function_call.py
luciusassistant/lucius_prompt.md
nexus/__init__.py
luciusassistant-0.4.dist-info/LICENSE
luciusassistant-0.4.dist-info/METADATA
luciusassistant-0.4.dist-info/WHEEL
luciusassistant-0.4.dist-info/top_level.txt
luciusassistant-0.4.dist-info/RECORD
