Metadata-Version: 2.1
Name: luciusassistant
Version: 0.4
Summary: An agentic AI assistant built on top of the Llama language model, designed to provide intelligent assistance through a robust function calling system. It offers seamless integration of chat capabilities with file operations and memory management.
Author: Matthew Sanchez
Author-email: 
Classifier: Programming Language :: Python :: 3
Classifier: License :: OSI Approved :: MIT License
Classifier: Operating System :: OS Independent
Requires-Python: >=3.10
License-File: LICENSE
Requires-Dist: chatollama
